[
    {
        "hero": "Slark",
        "url": "https://static.wikia.nocookie.net/dota2_ru_gamepedia/images/c/c0/Slark_rival_03_ru.mp3/revision/latest?cb=20170413151822",
        "lang": "ru",
        "lyrics": "Naga Siren minimap icon: Я тебя не слышу."
    },
    {
        "hero": "Clockwerk",
        "url": "https://static.wikia.nocookie.net/dota2_ru_gamepedia/images/0/0f/Ratt_level_13_ru.mp3/revision/latest?cb=20170409121101",
        "lang": "ru",
        "lyrics": "Всех раскручу, ха-ха!"
    }
]